crispy_bootstrap4/__init__.py
crispy_bootstrap4/templates/bootstrap4/accordion-group.html
crispy_bootstrap4/templates/bootstrap4/accordion.html
crispy_bootstrap4/templates/bootstrap4/betterform.html
crispy_bootstrap4/templates/bootstrap4/display_form.html
crispy_bootstrap4/templates/bootstrap4/errors.html
crispy_bootstrap4/templates/bootstrap4/errors_formset.html
crispy_bootstrap4/templates/bootstrap4/field.html
crispy_bootstrap4/templates/bootstrap4/inputs.html
crispy_bootstrap4/templates/bootstrap4/table_inline_formset.html
crispy_bootstrap4/templates/bootstrap4/uni_form.html
crispy_bootstrap4/templates/bootstrap4/uni_formset.html
crispy_bootstrap4/templates/bootstrap4/whole_uni_form.html
crispy_bootstrap4/templates/bootstrap4/whole_uni_formset.html
crispy_bootstrap4/templates/bootstrap4/layout/alert.html
crispy_bootstrap4/templates/bootstrap4/layout/attrs.html
crispy_bootstrap4/templates/bootstrap4/layout/baseinput.html
crispy_bootstrap4/templates/bootstrap4/layout/button.html
crispy_bootstrap4/templates/bootstrap4/layout/buttonholder.html
crispy_bootstrap4/templates/bootstrap4/layout/checkboxselectmultiple.html
crispy_bootstrap4/templates/bootstrap4/layout/checkboxselectmultiple_inline.html
crispy_bootstrap4/templates/bootstrap4/layout/column.html
crispy_bootstrap4/templates/bootstrap4/layout/div.html
crispy_bootstrap4/templates/bootstrap4/layout/field_errors.html
crispy_bootstrap4/templates/bootstrap4/layout/field_errors_block.html
crispy_bootstrap4/templates/bootstrap4/layout/field_file.html
crispy_bootstrap4/templates/bootstrap4/layout/field_with_buttons.html
crispy_bootstrap4/templates/bootstrap4/layout/fieldset.html
crispy_bootstrap4/templates/bootstrap4/layout/formactions.html
crispy_bootstrap4/templates/bootstrap4/layout/help_text.html
crispy_bootstrap4/templates/bootstrap4/layout/help_text_and_errors.html
crispy_bootstrap4/templates/bootstrap4/layout/inline_field.html
crispy_bootstrap4/templates/bootstrap4/layout/modal.html
crispy_bootstrap4-2024.10.dist-info/LICENSE
crispy_bootstrap4-2024.10.dist-info/METADATA
crispy_bootstrap4-2024.10.dist-info/WHEEL
crispy_bootstrap4-2024.10.dist-info/top_level.txt
crispy_bootstrap4-2024.10.dist-info/RECORD
