Metadata-Version: 2.1
Name: crispy-bootstrap4
Version: 2024.10
Summary: Bootstrap4 template pack for django-crispy-forms
Home-page: https://github.com/django-crispy-forms/crispy-bootstrap4
Author: David Smith
License: MIT
Project-URL: Issues, https://github.com/django-crispy-forms/crispy-bootstrap4/issues
Project-URL: CI, https://github.com/django-crispy-forms/crispy-bootstrap4/actions
Project-URL: Changelog, https://github.com/django-crispy-forms/crispy-bootstrap4/releases
Classifier: Environment :: Web Environment
Classifier: Development Status :: 5 - Production/Stable
Classifier: Framework :: Django
Classifier: Framework :: Django :: 4.2
Classifier: Framework :: Django :: 5.0
Classifier: Framework :: Django :: 5.1
Classifier: License :: OSI Approved :: MIT License
Classifier: Operating System :: OS Independent
Classifier: Programming Language :: Python :: 3
Classifier: Programming Language :: Python :: 3.8
Classifier: Programming Language :: Python :: 3.9
Classifier: Programming Language :: Python :: 3.10
Classifier: Programming Language :: Python :: 3.11
Classifier: Programming Language :: Python :: 3.12
Classifier: Topic :: Internet :: WWW/HTTP
Classifier: Topic :: Internet :: WWW/HTTP :: Dynamic Content
Classifier: Topic :: Software Development :: Libraries :: Python Modules
Requires-Python: >=3.8
License-File: LICENSE
